bitmerchant/__init__.py
bitmerchant/_version.py
bitmerchant/network.py
bitmerchant/wallet/__init__.py
bitmerchant/wallet/bip32.py
bitmerchant/wallet/keys.py
bitmerchant/wallet/utils.py
bitmerchant-0.1.8.dist-info/top_level.txt
bitmerchant-0.1.8.dist-info/METADATA
bitmerchant-0.1.8.dist-info/DESCRIPTION.rst
bitmerchant-0.1.8.dist-info/metadata.json
bitmerchant-0.1.8.dist-info/WHEEL
bitmerchant-0.1.8.dist-info/RECORD
