Metadata-Version: 1.1
Name: bitmerchant
Version: 0.1.8
Summary: Bitcoin/altcoin merchant tools
Home-page: https://github.com/sbuss/bitmerchant
Author: Steven Buss
Author-email: steven.buss@gmail.com
License: MIT License
Download-URL: https://github.com/sbuss/bitmerchant/tarball/v0.1.8
Platform: UNKNOWN
Classifier: Development Status :: 3 - Alpha
Classifier: Intended Audience :: Developers
Classifier: License :: OSI Approved :: MIT License
Classifier: Operating System :: OS Independent
Classifier: Programming Language :: Python
Classifier: Programming Language :: Python :: 2.5
Classifier: Programming Language :: Python :: 2.6
Classifier: Programming Language :: Python :: 2.7
Classifier: Programming Language :: Python :: 3
Classifier: Programming Language :: Python :: 3.0
Classifier: Programming Language :: Python :: 3.1
Classifier: Programming Language :: Python :: 3.2
Classifier: Programming Language :: Python :: 3.3
Classifier: Programming Language :: Python :: 3.4
